ciokatana/VERSION
ciokatana/__init__.py
ciokatana/post_install.py
ciokatana/scripts/create_fake_upload_files.py
ciokatana/scripts/mock_submission.json
ciokatana/shelf_items/ListRenderOutputs.py
ciokatana/shelf_items/ReloadConductor.py
ciokatana/shelf_items/ScanAssets.py
ciokatana/v1/Editor.py
ciokatana/v1/Node.py
ciokatana/v1/Panel.py
ciokatana/v1/Upgrade.py
ciokatana/v1/__init__.py
ciokatana/v1/configuration_tab.py
ciokatana/v1/const.py
ciokatana/v1/dialog.py
ciokatana/v1/preview_tab.py
ciokatana/v1/progress_tab.py
ciokatana/v1/reloader.py
ciokatana/v1/render_file_dialog.py
ciokatana/v1/response_tab.py
ciokatana/v1/setup.py
ciokatana/v1/tooltips.py
ciokatana/v1/utils.py
ciokatana/v1/validation.py
ciokatana/v1/validation_tab.py
ciokatana/v1/components/__init__.py
ciokatana/v1/components/buttoned_scroll_panel.py
ciokatana/v1/components/checkbox_grp.py
ciokatana/v1/components/combo_box_grp.py
ciokatana/v1/components/int_field_grp.py
ciokatana/v1/components/key_value_grp.py
ciokatana/v1/components/notice_grp.py
ciokatana/v1/components/render_node_table.py
ciokatana/v1/components/software_combo_box_grp.py
ciokatana/v1/components/text_field_grp.py
ciokatana/v1/components/text_grp.py
ciokatana/v1/components/widgets.py
ciokatana/v1/icons/ConductorConnect_24x24.png
ciokatana/v1/icons/ConductorError_24x24.png
ciokatana/v1/icons/ConductorHelp_24x24.png
ciokatana/v1/icons/ConductorInfo_24x24.png
ciokatana/v1/icons/ConductorShow_24x24.png
ciokatana/v1/icons/ConductorSubmit_24x24.png
ciokatana/v1/icons/ConductorSuccess_24x24.png
ciokatana/v1/icons/ConductorWarning_24x24.png
ciokatana/v1/model/__init__.py
ciokatana/v1/model/array_model.py
ciokatana/v1/model/asset_scraper.py
ciokatana/v1/model/assets_model.py
ciokatana/v1/model/collapsible_panel_model.py
ciokatana/v1/model/environment_model.py
ciokatana/v1/model/hardware_model.py
ciokatana/v1/model/jobs_model.py
ciokatana/v1/model/metadata_model.py
ciokatana/v1/model/misc_model.py
ciokatana/v1/model/project_model.py
ciokatana-0.1.7.dist-info/METADATA
ciokatana-0.1.7.dist-info/WHEEL
ciokatana-0.1.7.dist-info/top_level.txt
ciokatana-0.1.7.dist-info/RECORD
