Metadata-Version: 2.1
Name: ciokatana
Version: 0.1.7
Summary: Katana plugin for Conductor Cloud Rendering Platform.
Home-page: https://github.com/ConductorTechnologies/ciokatana
Author: conductor
Author-email: info@conductortech.com
Classifier: Operating System :: OS Independent
Classifier: Programming Language :: Python
Classifier: Topic :: Multimedia :: Graphics :: 3D Rendering
Requires-Dist: certifi==2019.11.28
Requires-Dist: ciocore==6.3.1-rc.3
Requires-Dist: ciopath<2.0.0,>=1.1.1
Requires-Dist: cioseq<1.0.0,>=0.3.0
Requires-Dist: json-stream<3.0.0,>=2.3.2
